{
  "project_info": {
    "project_number": "159601934733",
    "project_id": "upmate-armora",
    "storage_bucket": "upmate-armora.appspot.com"
  },
  "client": [
    {
      "client_info": {
        "mobilesdk_app_id": "1:159601934733:android:980399b87cb83321853dc4",
        "android_client_info": {
          "package_name": "com.armoratech.upmate"
        }
      },
      "oauth_client": [
        {
          "client_id": "159601934733-t79h80b8qc8gih3b0raqdr0gj34lh4e0.apps.googleusercontent.com",
          "client_type": 1,
          "android_info": {
            "package_name": "com.armoratech.upmate",
            "certificate_hash": "77d643c48eb2c5a5fec24ad451c63c9b49f55584"
          }
        },
        {
          "client_id": "159601934733-rdcro81bo8bv5f68vuje7q77m0bcl6c6.apps.googleusercontent.com",
          "client_type": 3
        }
      ],
      "api_key": [
        {
          "current_key": "AIzaSyDQVSeLnLEx0BW-04TJe7DZ_E_ju1kH35o"
        }
      ],
      "services": {
        "appinvite_service": {
          "other_platform_oauth_client": [
            {
              "client_id": "159601934733-rdcro81bo8bv5f68vuje7q77m0bcl6c6.apps.googleusercontent.com",
              "client_type": 3
            },
            {
              "client_id": "159601934733-6hh55qn625tbmcj0uf6oud79ilm2vcum.apps.googleusercontent.com",
              "client_type": 2,
              "ios_info": {
                "bundle_id": "com.armoratech.upmate"
              }
            }
          ]
        }
      }
    }
  ],
  "configuration_version": "1"
}